erica/__init__.py
erica-0.2.0.dist-info/LICENSE
erica-0.2.0.dist-info/WHEEL
erica-0.2.0.dist-info/METADATA
erica-0.2.0.dist-info/RECORD
