Metadata-Version: 2.1
Name: erica
Version: 0.2.0
Summary: flask-like zero denpendency web server.
Author: Ryu Juheon
Author-email: saidbysolo@gmail.com
Requires-Python: >=3.10,<4.0
Classifier: Programming Language :: Python :: 3
Classifier: Programming Language :: Python :: 3.10
